[{"id":"3002","meal":"G\u00f6kler; y\u0131ld\u0131zlar,g\u00fcne\u015fler, aylar, gezegenlerin Kendisini tesbih etti\u011fi Z\u00e2t\u0131n ad\u0131yla."},{"id":"3003","meal":"G\u00f6klerin; y\u0131ld\u0131z, g\u00fcne\u015f, ay ve gezegenlerinin diliyle Kendisini tesbih etti\u011fi z\u00e2t\u0131n ad\u0131yla. G\u00f6kteki y\u0131ld\u0131zlar say\u0131s\u0131nca Allah\u0027\u0131n sel\u00e2m\u0131, rahmeti ve bereketi sizin ve karde\u015flerinizin \u00fczerine olsun."},{"id":"3004","meal":"\u201c\u00c7\u00fcnk\u00fc, b\u00fct\u00fcn e\u015fya L\u00e2 il\u00e2he ill\u00e2 H\u00fb deyip, k\u00e2inat\u0131n az\u00eem halka-i zikrinde beraber zikrederek \u00e7al\u0131\u015f\u0131yorlar. Vakit-be-vakit, lisan-\u0131 istidat ile, Cen\u00e2b-\u0131 Haktan hukuk-u hayat\u0131n\u0131 \u2018Y\u00e2 Hak\u2019 deyip hazine-i rahmetten istiyorlar. Ba\u015ftan ba\u015fa da, hayata mazhariyetleri lisan\u0131yla \u2018Y\u00e2 Hayy\u2019 ismini zikrediyorlar.\u201d"},{"id":"3005","meal":"Temsilde tart\u0131\u015fma olmaz."},{"id":"3006","meal":"Allah\u0027\u0131m! Bize hakk\u0131 hak olarak g\u00f6ster ve ona ittiba etmekle bizi r\u0131z\u0131kland\u0131r."},{"id":"3008","meal":"\u0022Onu i\u015fitti\u011finizde, \u2018Bunu s\u00f6ylemek bize yak\u0131\u015fmaz. H\u00e2\u015f\u00e2, bu b\u00fcy\u00fck bir iftirad\u0131r\u0027 demeniz gerekmez miydi?\u0022 Nur S\u00fbresi, 24:16."},{"id":"3009","meal":"Namaz, dua, Peygamberimiz (sav)\u0027e salavat\u0131 halktan Hakka gidi\u015finin ifadesi."},{"id":"3010","meal":"Sel\u00e2m, sel\u00e2met, Peygamberimiz\u0027in (sav) Hak\u0027tan halka d\u00f6n\u00fc\u015f\u00fcn\u00fc ifade, O\u0027nun memuriyetini kabul edi\u015fimizin ifadesi.\u0027"},{"id":"3011","meal":"Efendimiz, Reisimiz..."},{"id":"3012","meal":"Allah\u0027\u0131m, Senin kulun ve resul\u00fcn olan efendimiz Muhammed\u0027e ve onun b\u00fct\u00fcn \u00e2l ve ashab\u0131na sal\u00e2t eyle."},{"id":"3013","meal":"\u0022E\u011fer g\u00f6klerde ve yerde Allah\u0027tan ba\u015fka il\u00e2hlar olsayd\u0131, ikisi de harap olup giderdi. Ar\u015f\u0131n Rabbi olan Allah, onlar\u0131n yak\u0131\u015ft\u0131rd\u0131klar\u0131 \u015feylerden m\u00fcnezzehtir.\u0022 Enbiy\u00e2 S\u00fbresi, 21:22."},{"id":"3015","meal":"\u0022B\u00fct\u00fcn dinlere \u00fcst\u00fcn k\u0131lmak \u00fczere Resul\u00fcn\u00fc hid\u00e2yet ve hak din ile g\u00f6nderen Odur.\u0022 Fetih S\u00fbresi, 48:28."},{"id":"3019","meal":"Diledi, istedi."},{"id":"3023","meal":"\u201cSonra Allah, bu kederin ard\u0131ndan size bir emniyet, bir uyuklama hali verdi...\u201d (\u00c2l-i \u0130mr\u00e2n S\u00fbresi, 3:154)"},{"id":"3025","meal":"\u0022Sen onlar\u0131n r\u00fck\u00fb ve secde ettiklerini g\u00f6r\u00fcrs\u00fcn.\u0022 Fetih S\u00fbresi, 48:29."},{"id":"3026","meal":"\u0022Onlar Allah\u0027\u0131n l\u00fctfunu ve r\u0131zas\u0131n\u0131 isterler.\u0022 Fetih S\u00fbresi, 48:29."},{"id":"3027","meal":"\u0022Y\u00fczlerinde secdelerin izlerinden ni\u015fanlar\u0131, al\u00e2metleri vard\u0131r.\u0022 Fetih S\u00fbresi, 48:29."},{"id":"3028","meal":"\u0022\u0130ncildeki vas\u0131flar\u0131 ise \u015f\u00f6yledir: \u2026\u0022 Fetih S\u00fbresi, 48:29."},{"id":"3029","meal":"\u0022Allah g\u00f6klerin ve yerin nurudur. Onun nurunun mis\u00e2li, bir l\u00e2mba yuvas\u0131 gibidir...\u0022 Nur S\u00fbresi, 24:35."},{"id":"3030","meal":"Ey b\u00fct\u00fcn nurlar Onun n\u00fbrunun ancak bir kesif g\u00f6lgesi olan Nurlar\u0131n N\u00fbru, Ey madd\u00ee ve m\u00e2nev\u00ee b\u00fct\u00fcn nurlar ve umum n\u00fbr\u00e2niyat Ondan feyiz alan Nurlar\u0131n M\u00fcnevviri, Ey her n\u00fbra ve n\u00fbr\u00e2n\u00eeye ve herbir nurlu mahl\u00fbka me\u015f\u00eeet ve kudretiyle s\u00fbret-i maddiye ve m\u00e2neviyesini veren Nurlar\u0131n Musavviri, Ey b\u00fct\u00fcn nurlar\u0131n b\u00fct\u00fcn keyfiy\u00e2t\u0131n\u0131 ilim ve ir\u00e2desiyle takdir eden ve madd\u00ee ve m\u00e2nev\u00ee miktarlar\u0131n\u0131 veren Nurlar\u0131n Mukaddiri, Ey b\u00fct\u00fcn nur ve n\u00fbr\u00e2n\u00eeleri b\u00fct\u00fcn lev\u00e2z\u0131m\u00e2t\u0131yla halk eden ve b\u00fct\u00fcn nurlar\u0131 sevk ve id\u00e2re ve tedbir ve teshir eden Nurlar\u0131n M\u00fcdebbiri, Ey b\u00fct\u00fcn nurlar\u0131 halk eden Nurlar\u0131n H\u00e2l\u0131k\u0131, Ey her nurdan \u00f6nce var olan N\u00fbr-u Ezel\u00ee, Ey b\u00fct\u00fcn nurlar\u0131n s\u00f6n\u00fcp gitmesinden sonra b\u00e2k\u00ee kalan N\u00fbr-u Sermed\u00ee, Ey N\u00fbru b\u00fct\u00fcn nurlar\u0131n fevkinde olan ve azamet-i n\u00fbr\u00e2niyetiyle b\u00fct\u00fcn mevc\u00fbd\u00e2ta h\u00fckmeden N\u00fbr-u Sem\u00e2v\u00e2t ve Arz, Ey hi\u00e7bir nur hi\u00e7bir cihetle Onun n\u00fbruna misil olamayan N\u00fbr-u Mukaddes ve Muall\u00e2 olan Allah\u2019\u0131m! Sen aczden ve \u015ferikten m\u00fcnezzeh ve mukaddessin. Senden ba\u015fka il\u00e2h yok. El-aman, el-aman! Bizi (ve Ali\u2019yi) Cehennem ate\u015finden kurtar. Bizi (ve Ali\u2019yi) iyiler z\u00fcmresiyle beraber Cennete koy. Bizim kalblerimizi ve onun kalbini, bizim kabirlerimizi ve onun kabrini iman ve Kur\u2019\u00e2n nuruyla nurland\u0131r, ya Rah\u00eem, ya Gaff\u00e2r! \u00c2lemlerde se\u00e7ilmi\u015f Muhammed\u2019e, onun tertemiz \u00e2line ve hay\u0131rl\u0131 Sahab\u00eelerine sal\u00e2t et. \u00c2min, \u00e2min, \u00e2min."},{"id":"3031","meal":"Ey b\u00fct\u00fcn nurlar Onun n\u00fbrunun ancak bir kesif g\u00f6lgesi olan Nurlar\u0131n N\u00fbru, Ey madd\u00ee ve m\u00e2nev\u00ee b\u00fct\u00fcn nurlar ve umum n\u00fbr\u00e2niyat Ondan feyiz alan Nurlar\u0131n M\u00fcnevviri, Ey her n\u00fbra ve n\u00fbr\u00e2n\u00eeye ve herbir nurlu mahl\u00fbka me\u015f\u00eeet ve kudretiyle s\u00fbret-i maddiye ve m\u00e2neviyesini veren Nurlar\u0131n Musavviri, Ey b\u00fct\u00fcn nurlar\u0131n b\u00fct\u00fcn keyfiy\u00e2t\u0131n\u0131 ilim ve ir\u00e2desiyle takdir eden ve madd\u00ee ve m\u00e2nev\u00ee miktarlar\u0131n\u0131 veren Nurlar\u0131n Mukaddiri, Ey b\u00fct\u00fcn nur ve n\u00fbr\u00e2n\u00eeleri b\u00fct\u00fcn lev\u00e2z\u0131m\u00e2t\u0131yla halk eden ve b\u00fct\u00fcn nurlar\u0131 sevk ve id\u00e2re ve tedbir ve teshir eden Nurlar\u0131n M\u00fcdebbiri, Ey b\u00fct\u00fcn nurlar\u0131 halk eden Nurlar\u0131n H\u00e2l\u0131k\u0131, Ey her nurdan \u00f6nce var olan N\u00fbr-u Ezel\u00ee, Ey b\u00fct\u00fcn nurlar\u0131n s\u00f6n\u00fcp gitmesinden sonra b\u00e2k\u00ee kalan N\u00fbr-u Sermed\u00ee, Ey N\u00fbru b\u00fct\u00fcn nurlar\u0131n fevkinde olan ve azamet-i n\u00fbr\u00e2niyetiyle b\u00fct\u00fcn mevc\u00fbd\u00e2ta h\u00fckmeden N\u00fbr-u Sem\u00e2v\u00e2t ve Arz, Ey hi\u00e7bir nur hi\u00e7bir cihetle Onun n\u00fbruna misil olamayan N\u00fbr-u Mukaddes ve Muall\u00e2 olan Allah\u2019\u0131m! Sen aczden ve \u015ferikten m\u00fcnezzeh ve mukaddessin. Senden ba\u015fka il\u00e2h yok. El-aman, el-aman! Bizi (ve Ali\u2019yi) Cehennem ate\u015finden kurtar. Bizi (ve Ali\u2019yi) iyiler z\u00fcmresiyle beraber Cennete koy. Bizim kalblerimizi ve onun kalbini, bizim kabirlerimizi ve onun kabrini iman ve Kur\u2019\u00e2n nuruyla nurland\u0131r, ya Rah\u00eem, ya Gaff\u00e2r! \u00c2lemlerde se\u00e7ilmi\u015f Muhammed\u2019e, onun tertemiz \u00e2line ve hay\u0131rl\u0131 Sahab\u00eelerine sal\u00e2t et. \u00c2min, \u00e2min, \u00e2min."},{"id":"3032","meal":"Allah\u2019\u0131n sel\u00e2m\u0131, rahmeti ve bereketi senin, annenin, karde\u015finin ve di\u011fer karde\u015flerinin \u00fczerine olsun."},{"id":"3033","meal":"\u0022Y\u0131ld\u0131zlar sa\u00e7\u0131ld\u0131\u011f\u0131 zaman.\u0022 \u0130nfitar S\u00fbresi, 82:2."},{"id":"3034","meal":"Kur\u0027\u00e2n\u0027\u0131n harfleri ve esrar\u0131 adedince, Allah\u0027\u0131n sel\u00e2m\u0131, rahmet ve bereketi \u00fczerinize olsun."},{"id":"3035","meal":"\u0022Allah rahmetine eri\u015ftirecektir. Muhakkak ki Allah\u0027\u0131n kudreti her\u015feye galiptir ve Onun her i\u015fi hikmet iledir.\u0022 Tevbe S\u00fbresi, 9:71."},{"id":"3036","meal":"\u0022Allah zulmetmez.\u0022 Tevbe S\u00fbresi, 9:70."},{"id":"3037","meal":"\u0022Siz Allah\u0027\u0131n dinine yard\u0131m ederseniz O da size yard\u0131m eder ve size sebat verir.\u0022 Muhammed S\u00fbresi, 47:7."},{"id":"3038","meal":"\u201cBirbirinizle iyilik ve takv\u00e2da yard\u0131mla\u015f\u0131n.\u201d M\u00e2ide S\u00fbresi, 5:2. * \u201cAllah\u2019a da itaat edin, Peygambere de itaat edin.\u201d M\u00e2ide S\u00fbresi, 5:92."},{"id":"3039","meal":"\u201c\u015e\u00fcphesiz ki Allah kat\u0131nda makbul olan din \u0130sl\u00e2m dinidir.\u201d \u00c2l-i \u0130mr\u00e2n S\u00fbresi, 3:19. * \u201cAllah\u2019\u0131n ipine hep birlikte s\u0131ms\u0131k\u0131 sar\u0131l\u0131n; ayr\u0131l\u0131\u011fa d\u00fc\u015f\u00fcp da\u011f\u0131lmay\u0131n.\u201d \u00c2l-i \u0130mran S\u00fbresi, 3:103. *  \u201cM\u00fc\u2019minler karde\u015ftirler.\u201d Hucur\u00e2t S\u00fbresi, 49:10."},{"id":"3040","meal":"\u0022Din nasihatt\u0131r. Din nasihatt\u0131r. Din nasihatt\u0131r.\u0022 M\u00fcslim, \u0130m\u00e2n: 95; Tirmiz\u00ee, Birr: 17; Nes\u00e2\u00ee, Bey\u0027a: 31; Darim\u00ee, Rikak: 41; M\u00fcsned, 1:351, 2:297, 4:102."},{"id":"3041","meal":"Allah en b\u00fcy\u00fckt\u00fcr, Allah en b\u00fcy\u00fckt\u00fcr. Allah\u0027tan ba\u015fka il\u00e2h yoktur O Allah en b\u00fcy\u00fckt\u00fcr. Allah en b\u00fcy\u00fckt\u00fcr. Ve hamd, ancak ona mahsustur."},{"id":"3042","meal":"\u0022Her nefis \u00f6l\u00fcm\u00fc tad\u0131c\u0131d\u0131r.\u0022 Ankebut S\u00fbresi, 29:57.  \u0022De ki: Onu ilk \u00f6nce kim yaratm\u0131\u015fsa tekrar O diriltecek. O her\u015feyin yat\u0131l\u0131\u015f\u0131n\u0131 hakk\u0131yla bilendir.\u0022 Y\u00e2sin S\u00fbresi, 36:79."},{"id":"3043","meal":"\u0022Sonra bir daha s\u00fbra \u00fcflenir. Ve onlar kabirlerinden kalkar.\u0022 Z\u00fcmer S\u00fbresi, 39:68."},{"id":"3044","meal":"\u0022M\u00fc\u015frikler ancak birer pisliktir.\u0022 Tevbe S\u00fbresi, 9:28.  \u0022Nice az topluluklar, nice kalabal\u0131k topluluklara Allah\u0027\u0131n izniyle galip gelmi\u015flerdir.\u0022 Bakara S\u00fbresi, 2:249."},{"id":"3045","meal":"\u0022D\u00fcnyadan da nasibini unutma.\u0022 Kasas S\u00fbresi, 28:77.  \u0022Allah adaleti, iyilik yapmay\u0131 ve iyi kullukta bulunmay\u0131 emreder.\u0022 Nahl S\u00fbresi, 16:90."},{"id":"3046","meal":"\u0022Kim nefsini tan\u0131rsa Rabbini de tan\u0131r.\u0022 Suy\u00fbt\u00ee, el-H\u00e2v\u00ee li\u0027l-Fet\u00e2v\u00e2, 2:451."},{"id":"3047","meal":"Ezelden ebede kadar hi\u00e7 kesintisiz Allah\u0027\u0131n sel\u00e2m\u0131, rahmet ve bereketi \u00fczerinize olsun."},{"id":"3048","meal":"\u0022Ak\u0131bet, Allah\u0027\u0131n emir ve yasaklar\u0131na kar\u015f\u0131 gelmekten sak\u0131nanlar\u0131nd\u0131r.\u0022 Kasas S\u00fbresi, 28:83. \u0022Allah\u0027a t\u00e2bi olan topluluk ger\u00e7ek galiplerin t\u00e2 kendisidir.\u0022 M\u00e2ide S\u00fbresi, 5:56."},{"id":"3049","meal":"\u0022Allah i\u00e7in sevmek.\u0022 Eb\u00fb D\u00e2v\u00fbd, S\u00fcnnet 15; Tirmiz\u00ee, K\u0131y\u00e2met 60; M\u00fcsned 3:438, 440."},{"id":"3050","meal":"Allah\u0027\u0131n sel\u00e2m\u0131, rahmeti ve bereketi sizin, anne ve baban\u0131z\u0131n ve karde\u015flerinizin \u00fczerine olsun."},{"id":"3051","meal":"\u0022Hi\u00e7bir \u015fey yoktur ki Allah\u0027\u0131 hamd ile tesbih etmesin.\u0022 \u0130sr\u00e2 S\u00fbresi, 17:44."},{"id":"3052","meal":"Allah\u0027\u0131n sel\u00e2m\u0131 sizin, anne ve baban\u0131z\u0131n, karde\u015flerinizin, Kur\u0027\u00e2n dersindeki arkada\u015flar\u0131n\u0131z\u0131n \u00fczerine olsun."},{"id":"3053","meal":"\u0022Siz Allah\u0027a ortak ko\u015fmaktan korkmazken, ben mi sizin ortak ko\u015ftuklar\u0131n\u0131zdan korkaca\u011f\u0131m?\u0022 En\u0027\u00e2m S\u00fbresi, 6:81."},{"id":"3054","meal":"B\u00e2t\u0131l dinlerden uzak, \u0130brahim\u2019in \u0130sl\u00e2m dinine uy!"},{"id":"3055","meal":"\u0022Sonra b\u00fct\u00fcn i\u015fler, sizin g\u00fcn\u00fcn\u00fczle bin sene kadar uzun olan k\u0131yamet g\u00fcn\u00fcnde Ona arz edilir.\u0022 Secde S\u00fbresi, 32:5."},{"id":"3056","meal":"\u0022Melekler ve Cebr\u00e2il, elli bin sene uzunlu\u011funda bir g\u00fcn olan k\u0131yamet g\u00fcn\u00fcnde, Allah\u0027\u0131n emrini almak \u00fczere Ar\u015fa y\u00fckselirler.\u0022 Me\u00e2ric S\u00fbresi, 70:4."},{"id":"3057","meal":"\u0130lim Allah kat\u0131ndad\u0131r. Yazd\u0131klar\u0131n\u0131n s\u0131rlar\u0131n\u0131 en iyi Allah bilir."},{"id":"3058","meal":"Allah\u0027\u0131n (cc) Ferd, Hayy, Kayy\u00fbm, Hakem, Adl, Kudd\u00fbs isimleri."},{"id":"3059","meal":"\u00d6yle bir z\u00e2t\u0131n ad\u0131yla ki, \u201cYedi g\u00f6kle yer ve onlar\u0131n i\u00e7indekiler Onu tesbih eder. Hi\u00e7bir \u015fey yoktur ki Onu \u00f6v\u00fcp tesbih etmesin.\u201d (\u0130sr\u00e2 S\u00fbresi, 17:44.) * Allah\u0027\u0131n sel\u00e2m\u0131, rahmeti, ve berek\u00e2t\u0131 \u00fczerinize olsun."},{"id":"3060","meal":"\u0022Allah\u0027\u0131n mescidlerinde Allah\u0027\u0131n ad\u0131n\u0131n an\u0131lmas\u0131na m\u00e2ni olan.\u0022 Bakara S\u00fbresi, 2:114."},{"id":"3061","meal":"\u0022Derken m\u00fc\u0027minlerle onlar\u0131n aras\u0131na bir duvar \u00e7ekilir ki, onun bir kap\u0131s\u0131 vard\u0131r; i\u00e7erisi rahmet, d\u0131\u015f taraf\u0131 ise azapt\u0131r.\u0022 Had\u00eed S\u00fbresi, 57:13."},{"id":"3064","meal":"Gidiniz siz rafizilerdensiniz"},{"id":"3065","meal":"el-Muaydi\u0027yi i\u015fitmen, onu g\u00f6rmenden daha hay\u0131rl\u0131d\u0131r."},{"id":"3066","meal":"\u0022Peygamber (a.s.m.), \u00fczerinde siyah y\u00fcnden yap\u0131lm\u0131\u015f nak\u0131\u015fl\u0131 bir \u00f6rt\u00fcyle sabahleyin evden \u00e7\u0131kt\u0131. O esnada Hasan bin Ali (r.a.) geldi. Hemen onu \u00f6rt\u00fcn\u00fcn alt\u0131na ald\u0131. Sonra H\u00fcseyin (r.a.) geldi. O da onunla beraber \u00f6rt\u00fcn\u00fcn alt\u0131na girdi. Sonra F\u00e2t\u0131ma (r.a.) geldi. Onu da i\u00e7eri ald\u0131. Sonra Ali (r.a.) geldi. Onu da i\u00e7eri ald\u0131. Ve sonra \u015f\u00f6yle dedi: \u2018Ey Peygamber \u00e2ilesi, Allah g\u00fcnahlar\u0131n\u0131z\u0131 giderip sizi tertemiz yapmak istiyor.\u0022 (Ahz\u00e2b S\u00fbresi, 33:33.) M\u00fcslim, Fad\u00e2il\u00fc\u0027s-Sah\u00e2be: 61, hadis no: 2424."},{"id":"3067","meal":"\u015eifa istemek."},{"id":"3068","meal":"\u015eefaat talep etmek."},{"id":"3069","meal":"\u201cBende be\u015f \u015fey vard\u0131r ki, onlarla veb\u00e2 ate\u015finin yang\u0131n\u0131n\u0131 s\u00f6nd\u00fcr\u00fcr\u00fcm:"},{"id":"3070","meal":"Mustafa (a.s.m.), Murtaz\u00e2 Ali (r.a.), onun iki o\u011flu Hasan ve H\u00fcseyin (r.a.) ve F\u00e2t\u0131ma (r.a.). Mecmuat\u00fc\u2019l-Ahz\u00e2b, 3:505."},{"id":"3071","meal":"\u0022Erkek \u00e7ocuk k\u0131z gibi de\u011fildir.\u0022 \u00c2l-i \u0130mr\u00e2n S\u00fbresi, 3:36."},{"id":"3072","meal":"M\u00e2n\u00e2s\u0131 kendisine del\u00e2let eder."},{"id":"3073","meal":"M\u00e2n\u00e2s\u0131 ba\u015fkas\u0131na del\u00e2let eder."},{"id":"3074","meal":"Sahihtir."},{"id":"3075","meal":"\u0022Onlar, Allah\u0027\u0131n kendilerine pek b\u00fcy\u00fck nimetler ba\u011f\u0131\u015flad\u0131\u011f\u0131 peygamberler, s\u0131dd\u0131klar, \u015fehidler ve salih kimselerle beraberdirler.\u0022 Nis\u00e2 S\u00fbresi, 4:69."},{"id":"3076","meal":"\u0022Ey \u00eem\u00e2n edenler! Allah\u0027\u0131 \u00e7ok zikredin. Sabah ak\u015fam Onu tesbih edin. Odur ki, sizi ink\u00e2r karanl\u0131klar\u0131ndan nura \u00e7\u0131karmak i\u00e7in rahmetine eri\u015ftirir; melekler de ba\u011f\u0131\u015flanman\u0131z i\u00e7in dua ederler. M\u00fc\u0027minler i\u00e7in O \u00e7ok merhametlidir. Ona kavu\u015ftuklar\u0131 g\u00fcn Allah\u0027\u0131n m\u00fc\u0027minlere hediyesi sel\u00e2md\u0131r, her t\u00fcrl\u00fc korkudan emniyet ve sel\u00e2met m\u00fcjdesidir."},{"id":"3077","meal":"\u0022\u2026sizi ink\u00e2r karanl\u0131klar\u0131ndan nura \u00e7\u0131karmak i\u00e7in rahmetine eri\u015ftirir. M\u00fc\u0027minler i\u00e7in O \u00e7ok merhametlidir.\u0022 Ahzap S\u00fbresi, 33:43."},{"id":"3078","meal":"\u0022\u2026nura \u00e7\u0131karmak i\u00e7in rahmetine eri\u015ftirir. M\u00fc\u0027minler i\u00e7in O \u00e7ok merhametlidir.\u0022 Ahzap S\u00fbresi, 33:43."},{"id":"3079","meal":"\u0022\u2026 Biz seni insanlar i\u00e7in bir \u015fahit, bir m\u00fcjdeci olarak g\u00f6nderdik.\u0022 Ahzap S\u00fbresi, 33:45."},{"id":"3080","meal":"\u0022\u2026 Ve sak\u0131nd\u0131rc\u0131. Allah yoluna \u00e7a\u011f\u0131r\u0131c\u0131.\u0022 Ahzap S\u00fbresi, 33:46."},{"id":"3081","meal":"\u0022\u2026 Allah yolunda \u00e7a\u011f\u0131r\u0131c\u0131\u2026\u0022 Ahzap S\u00fbresi, 33:46."},{"id":"3082","meal":"Davet edici..."},{"id":"3083","meal":"\u0022\u2026 Allah yolunda \u00e7a\u011f\u0131r\u0131c\u0131\u2026\u0022 Ahzap S\u00fbresi, 33:46."},{"id":"3084","meal":"\u0022\u2026 Onun izniyle, nur sa\u00e7an bir kandil\u2026\u0022 Ahzap S\u00fbresi, 33:46."},{"id":"3085","meal":"\u0022Nur sa\u00e7an kandil.\u0022 Ahzap S\u00fbresi, 33:46."},{"id":"3086","meal":"nurlu, nur sa\u00e7an, etraf\u0131 ayd\u0131nlatan."},{"id":"3088","meal":"Allah\u0027tan (b\u00fcy\u00fck bir l\u00fctfa eri\u015feceklerini) m\u00fc\u0027minlere m\u00fcjdele.\u0022 Ahzap S\u00fbresi, 33:47."},{"id":"3089","meal":"\u0022Pek b\u00fcy\u00fck bir l\u00fbtuf ve ihsan.\u0022 Ahz\u00e2b S\u00fbresi, 33:47."},{"id":"3090","meal":"bir l\u00fctuf olarak"},{"id":"3091","meal":"Ve Allah\u0027\u0131n sal\u00e2t ve sel\u00e2m\u0131 Muhammed\u0027in (a.s.m.) ve onun \u00e2linin, ashab\u0131n\u0131n ve iyi ve temiz kimseler olan b\u00fct\u00fcn ehl-i beytinin \u00fczerine olsun. \u00c2min. \u00c2min. \u00c2min. Peygamberlerin efendisinin h\u00fcrmetine. Alemlerin Rabbi olan Allah\u0027a hamd olsun."},{"id":"3092","meal":"yard\u0131mla\u015f\u0131n\u0131z"},{"id":"3093","meal":"Yazd\u0131\u011f\u0131n\u0131z ve yazaca\u011f\u0131n\u0131z Risale-i Nur\u0027lar\u0131n harfleri adedince Allah\u0027\u0131n sel\u00e2m\u0131, rahmeti ve bereketi \u00fczerinize olsun."},{"id":"3094","meal":"\u0022De ki: Ey g\u00fcnahta a\u015f\u0131r\u0131 giderek nefislerine zulmetmi\u015f olan kullar\u0131m!\u0022 Z\u00fcmer S\u00fbresi, 39:53."},{"id":"3095","meal":"\u0022Belki sevmedi\u011finiz \u015fey hakk\u0131n\u0131zda hay\u0131rl\u0131d\u0131r. Bazan da sevdi\u011finiz bir\u015fey sizin i\u00e7in \u015fer olur. Allah her\u015feyi bilir, siz bilmezsiniz.\u0022 Bakara S\u00fbresi, 2:216. \u0022E\u011fer siz onlardan ho\u015flanmayacak olsan\u0131z bile, olur ki sizin ho\u015funuza gitmeyen bir\u015feyde Allah pek \u00e7ok hay\u0131r yarat\u0131r.\u0022 Nis\u00e2 S\u00fbresi, 4:19."},{"id":"3096","meal":"\u201cKim beni isterse beni bulur.\u201d * \u201cM\u00fc\u2019minler i\u00e7in Allah \u00e7ok merhametlidir.\u201d Ahz\u00e2b S\u00fbresi, 33:43. * \u201cAllah\u2019\u0131 \u00e7ok ba\u011f\u0131\u015flay\u0131c\u0131 ve \u00e7ok merhamet edici bulur.\u201d Nis\u00e2 S\u00fbresi, 4:110."},{"id":"3097","meal":"\u0022\u00c2limler peygamberlerin miras\u00e7\u0131lar\u0131d\u0131rlar.\u0022 Buhar\u00ee, \u0130lim: 10; Eb\u00fb D\u00e2vud, \u0130lim: 1; \u0130bn-i M\u00e2ce, Mukaddime: 17; D\u00e2rim\u00ee, Mukaddime: 32; M\u00fcsned: 5:196.  \u0022\u00dcmmetimin \u00e2limleri, \u0130srailo\u011fullar\u0131n\u0131n peygamberleri gibidir.\u0022 el-Acl\u00fbn\u00ee, Ke\u015ff\u00fc\u0027l-Haf\u00e2: 2:64; Tecrid-i Sarih Terc\u00fcmesi: 1:107."},{"id":"3098","meal":"\u201cOnun r\u0131zas\u0131na ula\u015ft\u0131racak vesileleri aray\u0131n ve Onun yolunda cihad edin.\u201d M\u00e2ide S\u00fbresi, 5:35. * \u201cOnlar ise ne g\u00fczel arkada\u015flard\u0131r!\u201d Nis\u00e2 S\u00fbresi, 4:69."},{"id":"3099","meal":"\u0022Kitaba s\u0131m s\u0131k\u0131 sar\u0131lanlara gelince...\u0022 A\u0027r\u00e2f S\u00fbresi, 7:170.  \u0022Allah\u0027\u0131n ipine hep birlikte s\u0131m s\u0131k\u0131 sar\u0131l\u0131n.\u0022 \u00c2l-i \u0130mran S\u00fbresi, 3:103.  \u0022Her kim Allah\u0027a s\u0131\u011f\u0131n\u0131r ve Onun dinine yap\u0131\u015f\u0131rsa, i\u015fte o k\u00fcfre d\u00fc\u015fmekten korunup do\u011fru yola ula\u015ft\u0131r\u0131lm\u0131\u015ft\u0131r.\u0022 \u00c2l-i \u0130mran S\u00fbresi, 3:101.  \u0022Allah\u0027a iman eden, hi\u00e7 kopmayacak bir zincir-i nuran\u00eeye yap\u0131\u015f\u0131r, temess\u00fck eder.\u0022 Bakara S\u00fbresi, 2:256; Lokman S\u00fbresi, 31:22.  \u0022Biz Kur\u0027\u00e2n\u0027dan m\u00fc\u0027minler i\u00e7in bir \u015fifa ve rahmet olan \u015feyi indiriyoruz.\u0022 \u0130sr\u00e2 S\u00fbresi, 17:82.  \u0022\u0130\u015fte bu \u00e2yetler, insanlara hakikati ap a\u00e7\u0131k g\u00f6steren bir beyan ve takv\u00e2 sahipleri i\u00e7in bir hidayet rehberi ve bir \u00f6\u011f\u00fctt\u00fcr.\u0022 \u00c2l-i \u0130mran S\u00fbresi, 3:138.  \u0022Bunlar Allah\u0027\u0131n s\u0131n\u0131rlar\u0131d\u0131r.\u0022 Bakara S\u00fbresi, 2:187. \u0022Ger\u00e7ekten size bir n\u00fbr ve hakk\u0131 ap a\u00e7\u0131k bildiren bir kitap gelmi\u015ftir.\u0022 M\u00e2ide S\u00fbresi, 5:15."}]